pyMPPost/__init__.py
pyMPPost/cross_correlation.py
pyMPPost/cython_functs.cpython-39-darwin.so
pyMPPost/cython_functs.pyx
pyMPPost/multiplicity.py
pyMPPost/pulse_height.py
pyMPPost/pyMPPost.py
pymppost-0.0.9.7.dist-info/METADATA
pymppost-0.0.9.7.dist-info/WHEEL
pymppost-0.0.9.7.dist-info/entry_points.txt
pymppost-0.0.9.7.dist-info/top_level.txt
pymppost-0.0.9.7.dist-info/RECORD
